gli_py/__init__.py
gli_py/error_codes.json
gli_py/error_handling.py
gli_py/glinet.py
gli_py-0.0.18.dist-info/LICENSE
gli_py-0.0.18.dist-info/METADATA
gli_py-0.0.18.dist-info/WHEEL
gli_py-0.0.18.dist-info/RECORD
