Metadata-Version: 2.1
Name: gli-py
Version: 0.0.18
Summary: A python 3 API wrapper for GL-inet routers for consumption by Home Assistant
License: GNU GENERAL PUBLIC LICENSE
Author: HarvsG
Author-email: doctor@codingdoctor.co.uk
Requires-Python: >=3.8,<4.0
Classifier: License :: Other/Proprietary License
Classifier: Programming Language :: Python :: 3
Classifier: Programming Language :: Python :: 3.8
Classifier: Programming Language :: Python :: 3.9
Classifier: Programming Language :: Python :: 3.10
Classifier: Programming Language :: Python :: 3.11
Requires-Dist: uplink (==0.9.7)
